tihan/sdv/securetransfer/__init__.py
tihan/sdv/securetransfer/aes_utils.py
tihan/sdv/securetransfer/ca.py
tihan/sdv/securetransfer/config.py
tihan/sdv/securetransfer/file_transfer.py
tihan/sdv/securetransfer/rsa_utils.py
tihan/sdv/visualizer/__init__.py
tihan/sdv/visualizer/calibrate.py
tihan/sdv/visualizer/parking_assist.py
tihan/sdv/visualizer/parking_color_graded.py
tihan/sdv/visualizer/ultrasonic.py
tihan_sdv-0.1.5.dist-info/METADATA
tihan_sdv-0.1.5.dist-info/WHEEL
tihan_sdv-0.1.5.dist-info/top_level.txt
tihan_sdv-0.1.5.dist-info/RECORD
